GoogleActions/Action.py
GoogleActions/AndroidApp.py
GoogleActions/AppResponse.py
GoogleActions/Argument.py
GoogleActions/BasicCard.py
GoogleActions/Button.py
GoogleActions/CancellationInfo.py
GoogleActions/CarouselBrowse.py
GoogleActions/CarouselBrowseItem.py
GoogleActions/CarouselItem.py
GoogleActions/CarouselSelect.py
GoogleActions/Cell.py
GoogleActions/ColumnProperties.py
GoogleActions/CustomPushMessage.py
GoogleActions/Date.py
GoogleActions/DateTime.py
GoogleActions/ExpectedInput.py
GoogleActions/ExpectedIntent.py
GoogleActions/Extension.py
GoogleActions/FinalResponse.py
GoogleActions/FulfillmentInfo.py
GoogleActions/Google.py
GoogleActions/Image.py
GoogleActions/InTransitInfo.py
GoogleActions/InputPrompt.py
GoogleActions/Item.py
GoogleActions/LatLng.py
GoogleActions/LineItemUpdate.py
GoogleActions/LinkOutSuggestion.py
GoogleActions/ListItem.py
GoogleActions/ListSelect.py
GoogleActions/Location.py
GoogleActions/MediaObject.py
GoogleActions/MediaResponse.py
GoogleActions/Money.py
GoogleActions/OpenUrlAction.py
GoogleActions/OptionInfo.py
GoogleActions/OptionValueSpec.py
GoogleActions/OrderState.py
GoogleActions/OrderUpdate.py
GoogleActions/PostalAddress.py
GoogleActions/Price.py
GoogleActions/Receipt.py
GoogleActions/RejectionInfo.py
GoogleActions/ResponseMetadata.py
GoogleActions/ReturnInfo.py
GoogleActions/RichResponse.py
GoogleActions/Row.py
GoogleActions/SelectItem.py
GoogleActions/SimpleResponse.py
GoogleActions/SimpleSelect.py
GoogleActions/Status.py
GoogleActions/StructuredResponse.py
GoogleActions/Suggestion.py
GoogleActions/TableCard.py
GoogleActions/Target.py
GoogleActions/TimeOfDay.py
GoogleActions/UserNotification.py
GoogleActions/VersionsFilter.py
GoogleActions/__init__.py
GoogleActions-0.3.dist-info/LICENSE
GoogleActions-0.3.dist-info/METADATA
GoogleActions-0.3.dist-info/WHEEL
GoogleActions-0.3.dist-info/top_level.txt
GoogleActions-0.3.dist-info/RECORD
