Metadata-Version: 2.1
Name: GoogleActions
Version: 0.3
Summary: A Python Library to interface with GoogleActions
Home-page: https://github.com/mayankberi1/GoogleActions
Author: Mayank Beri
Author-email: mayank@logicfactory.com.au
License: UNKNOWN
Platform: UNKNOWN
Classifier: Programming Language :: Python :: 3
Classifier: License :: OSI Approved :: GNU Lesser General Public License v3 or later (LGPLv3+)
Classifier: Operating System :: OS Independent
Requires-Python: >=3.6
